torcy/__init__.py
torcy/__main__.py
torcy/core.py
torcy-1.0.0.dist-info/licenses/LICENCE
torcy-1.0.0.dist-info/METADATA
torcy-1.0.0.dist-info/WHEEL
torcy-1.0.0.dist-info/entry_points.txt
torcy-1.0.0.dist-info/top_level.txt
torcy-1.0.0.dist-info/RECORD
