Metadata-Version: 2.4
Name: torcy
Version: 1.0.0
Summary: Aesthetic and smart PyTorch environment tester
Author-email: TOT <tot@example.com>
License: MIT
Keywords: pytorch,tester,gpu,cuda,torch,cli
Classifier: Programming Language :: Python :: 3
Classifier: Operating System :: OS Independent
Requires-Python: >=3.8
License-File: LICENCE
Dynamic: license-file
